npri/__init__.py
npri/npri.py
npri-0.0.5.dist-info/LICENSE
npri-0.0.5.dist-info/WHEEL
npri-0.0.5.dist-info/METADATA
npri-0.0.5.dist-info/RECORD
