Metadata-Version: 2.1
Name: npri
Version: 0.0.5
Summary: A Python package providing easy-to-use code that returns recently reported emissions from facilities, socio-economic information for places, emissions records for specific companies and industries, and emissions trends over time
Author-email: Eric Nost <enost@uoguelph.ca>
Classifier: Programming Language :: Python :: 3
Classifier: License :: OSI Approved :: GNU General Public License v3 (GPLv3)
Classifier: Operating System :: OS Independent
Classifier: Topic :: Scientific/Engineering :: GIS
Classifier: Topic :: Scientific/Engineering :: Information Analysis
Requires-Dist: folium>=0.14.0
Requires-Dist: geopandas>=0.9.0
Requires-Dist: ipython>=7.29.0
Requires-Dist: ipywidgets>=7.6.5
Requires-Dist: pandas>=1.3.4
Project-URL: Home, https://github.com/npri-tools/npri/
Project-URL: Issues, https://github.com/npri-tools/npri/issues
